algernon/__init__.py
algernon/agent.py
algernon/memory.py
algernon-0.0.1.dev2.dist-info/DESCRIPTION.rst
algernon-0.0.1.dev2.dist-info/METADATA
algernon-0.0.1.dev2.dist-info/RECORD
algernon-0.0.1.dev2.dist-info/WHEEL
algernon-0.0.1.dev2.dist-info/metadata.json
algernon-0.0.1.dev2.dist-info/top_level.txt
