Metadata-Version: 2.0
Name: algernon
Version: 0.0.1.dev2
Summary: Reinforcement learning framework with scikit like interface
Home-page: https://github.com/Lewuathe/algernon
Author: Kai Sasaki
Author-email: lewuathe@me.com
License: MIT
Keywords: deeplearning reinforcement_learning
Platform: UNKNOWN
Classifier: Development Status :: 3 - Alpha
Classifier: Intended Audience :: Developers
Classifier: License :: OSI Approved :: MIT License
Classifier: Programming Language :: Python :: 2
Classifier: Programming Language :: Python :: 3
Requires-Dist: keras
Requires-Dist: numpy
